model3501lib/__init__.py
model3501lib/cdstress_off.py
model3501lib/cdstress_on.py
model3501lib/emulate_charge.py
model3501lib/findDevice.py
model3501lib/getpower_role.py
model3501lib/getrdo.py
model3501lib/pdcaptive_cables.py
model3501lib/pdcharger_port.py
model3501lib/reconnect.py
model3501lib/set_speed.py
model3501api-1.0.6.dist-info/LICENSE
model3501api-1.0.6.dist-info/METADATA
model3501api-1.0.6.dist-info/WHEEL
model3501api-1.0.6.dist-info/top_level.txt
model3501api-1.0.6.dist-info/RECORD
