Metadata-Version: 2.1
Name: model3501api
Version: 1.0.6
Summary: API for MCCI Type C Super MUTT Model 3501.
Home-page: https://github.com/mcci-usb/model3501lib
Author: MCCI Corporation
Author-email: vinayn@mcci.com
Classifier: Programming Language :: Python :: 3
Classifier: License :: OSI Approved :: zlib/libpng License
Classifier: Operating System :: OS Independent
Requires-Python: >=3.8
License-File: LICENSE
Requires-Dist: pyusb
